youtube_dl/YoutubeDL.py
youtube_dl/__init__.py
youtube_dl/__main__.py
youtube_dl/aes.py
youtube_dl/cache.py
youtube_dl/compat.py
youtube_dl/jsinterp.py
youtube_dl/options.py
youtube_dl/socks.py
youtube_dl/swfinterp.py
youtube_dl/update.py
youtube_dl/utils.py
youtube_dl/version.py
youtube_dl/downloader/__init__.py
youtube_dl/downloader/common.py
youtube_dl/downloader/dash.py
youtube_dl/downloader/external.py
youtube_dl/downloader/f4m.py
youtube_dl/downloader/fragment.py
youtube_dl/downloader/hls.py
youtube_dl/downloader/http.py
youtube_dl/downloader/ism.py
youtube_dl/downloader/rtmp.py
youtube_dl/downloader/rtsp.py
youtube_dl/extractor/__init__.py
youtube_dl/extractor/abc.py
youtube_dl/extractor/abcnews.py
youtube_dl/extractor/abcotvs.py
youtube_dl/extractor/academicearth.py
youtube_dl/extractor/acast.py
youtube_dl/extractor/adn.py
youtube_dl/extractor/adobeconnect.py
youtube_dl/extractor/adobepass.py
youtube_dl/extractor/adobetv.py
youtube_dl/extractor/adultswim.py
youtube_dl/extractor/aenetworks.py
youtube_dl/extractor/afreecatv.py
youtube_dl/extractor/airmozilla.py
youtube_dl/extractor/aliexpress.py
youtube_dl/extractor/aljazeera.py
youtube_dl/extractor/allocine.py
youtube_dl/extractor/alphaporno.py
youtube_dl/extractor/amara.py
youtube_dl/extractor/amcnetworks.py
youtube_dl/extractor/americastestkitchen.py
youtube_dl/extractor/amp.py
youtube_dl/extractor/animeondemand.py
youtube_dl/extractor/anvato.py
youtube_dl/extractor/aol.py
youtube_dl/extractor/apa.py
youtube_dl/extractor/aparat.py
youtube_dl/extractor/appleconnect.py
youtube_dl/extractor/applepodcasts.py
youtube_dl/extractor/appletrailers.py
youtube_dl/extractor/archiveorg.py
youtube_dl/extractor/arcpublishing.py
youtube_dl/extractor/ard.py
youtube_dl/extractor/arkena.py
youtube_dl/extractor/arnes.py
youtube_dl/extractor/arte.py
youtube_dl/extractor/asiancrush.py
youtube_dl/extractor/atresplayer.py
youtube_dl/extractor/atttechchannel.py
youtube_dl/extractor/atvat.py
youtube_dl/extractor/audimedia.py
youtube_dl_hva-2021.4.17.dist-info/AUTHORS
youtube_dl_hva-2021.4.17.dist-info/LICENSE
youtube_dl_hva-2021.4.17.dist-info/METADATA
youtube_dl_hva-2021.4.17.dist-info/WHEEL
youtube_dl_hva-2021.4.17.dist-info/entry_points.txt
youtube_dl_hva-2021.4.17.dist-info/top_level.txt
youtube_dl_hva-2021.4.17.dist-info/RECORD
